[
  {
    "date": "2026-07-12 20:02",
    "city": "Prague",
    "country": "Czech Republic",
    "latin": "Tanacetum vulgare",
    "common": "Tansy",
    "note": "Blooming with vibrant yellow",
    "phenology": "Flowering",
    "compound_name": "Thujone",
    "compound": "Toxic to insects and humans",
    "season": "Summer",
    "temp": 25,
    "condition": "Partly cloudy",
    "image_url": "https://image.pollinations.ai/prompt/Fine%20botanical%20illustration%20of%20Tansy%2C%20traditional%20ukiyo-e%20woodblock%20print%20style%2C%20natural%20botanical%20colors%2C%20precise%20ink%20outlines%2C%20ivory%20paper%20texture%2C%20full%20plant%20with%20stem%20leaves%20and%20flowers%2C%20botanically%20accurate%2C%20soft%20watercolor%20wash%2C%20no%20text%2C%20no%20labels%2C%20museum%20quality%20print?width=800&height=920&seed=56732&nologo=true&t=1783886568"
  },
  {
    "date": "2026-07-12 15:39",
    "city": "Helsinki",
    "country": "Finland",
    "latin": "Campanula rotundifolia",
    "common": "Harebell",
    "note": "Dainty bells sway gently",
    "phenology": "Flowering",
    "compound_name": "Ursolic acid",
    "compound": "Rare due to complex synthesis",
    "season": "Summer",
    "temp": 25,
    "condition": "Partly cloudy",
    "image_url": "https://image.pollinations.ai/prompt/Fine%20botanical%20illustration%20of%20Harebell%2C%20traditional%20ukiyo-e%20woodblock%20print%20style%2C%20natural%20botanical%20colors%2C%20precise%20ink%20outlines%2C%20ivory%20paper%20texture%2C%20full%20plant%20with%20stem%20leaves%20and%20flowers%2C%20botanically%20accurate%2C%20soft%20watercolor%20wash%2C%20no%20text%2C%20no%20labels%2C%20museum%20quality%20print?width=800&height=920&seed=34065&nologo=true&t=1783870795"
  },
  {
    "date": "2026-07-12 12:54",
    "city": "Tbilisi",
    "country": "Georgia",
    "latin": "Paliurus spina-christi",
    "common": "Christ's Thorn",
    "note": "Blooming with vibrant flowers",
    "phenology": "Flowering",
    "compound_name": "Ursolic acid",
    "compound": "Rare due to complex synthesis",
    "season": "Summer",
    "temp": 30,
    "condition": "Partly cloudy",
    "image_url": "https://image.pollinations.ai/prompt/Fine%20botanical%20illustration%20of%20Paliurus%20spina-christi%2C%20traditional%20ukiyo-e%20woodblock%20print%20style%2C%20natural%20botanical%20colors%2C%20precise%20ink%20outlines%2C%20ivory%20paper%20texture%2C%20full%20plant%20with%20stem%20leaves%20and%20flowers%2C%20botanically%20accurate%2C%20soft%20watercolor%20wash%2C%20no%20text%2C%20no%20labels%2C%20museum%20quality%20print?width=800&height=920&seed=95755&nologo=true&t=1783860887"
  },
  {
    "date": "2026-07-12 12:49",
    "city": "Oslo",
    "country": "Norway",
    "latin": "Campanula rotundifolia",
    "common": "Harebell",
    "note": "Dainty bells sway gently",
    "phenology": "Flowering",
    "compound_name": "Ursolic acid",
    "compound": "Rare antioxidant properties",
    "season": "Summer",
    "temp": 25,
    "condition": "Clear sky",
    "image_url": "https://image.pollinations.ai/prompt/Fine%20botanical%20illustration%20of%20Harebell%2C%20traditional%20ukiyo-e%20woodblock%20print%20style%2C%20natural%20botanical%20colors%2C%20precise%20ink%20outlines%2C%20ivory%20paper%20texture%2C%20full%20plant%20with%20stem%20leaves%20and%20flowers%2C%20botanically%20accurate%2C%20soft%20watercolor%20wash%2C%20no%20text%2C%20no%20labels%2C%20museum%20quality%20print?width=800&height=920&seed=76158&nologo=true&t=1783860556"
  },
  {
    "date": "2026-07-12 11:45",
    "city": "Lisbon",
    "country": "Portugal",
    "latin": "Lavandula stoechas",
    "common": "Spanish lavender",
    "note": "Dancing in the warm breeze",
    "phenology": "Flowering",
    "compound_name": "Linalool",
    "compound": "Rare calming properties found",
    "season": "Summer",
    "temp": 23,
    "condition": "Partly cloudy",
    "image_url": "https://image.pollinations.ai/prompt/Fine%20botanical%20illustration%20of%20Lavandula%20stoechas%2C%20traditional%20ukiyo-e%20woodblock%20print%20style%2C%20natural%20botanical%20colors%2C%20precise%20ink%20outlines%2C%20ivory%20paper%20texture%2C%20full%20plant%20with%20stem%20leaves%20and%20flowers%2C%20botanically%20accurate%2C%20soft%20watercolor%20wash%2C%20no%20text%2C%20no%20labels%2C%20museum%20quality%20print?width=800&height=920&seed=71378&nologo=true&t=1783856700"
  },
  {
    "date": "2026-07-12 07:55",
    "city": "Auckland",
    "country": "New Zealand",
    "latin": "Leptinella squalida",
    "common": "Brass Buttons",
    "note": "Delicate buttons unfolding slowly",
    "phenology": "Dormant",
    "compound_name": "Flavonoids",
    "compound": "Rare antioxidant properties found",
    "season": "Winter",
    "temp": 10,
    "condition": "Clear sky",
    "image_url": "https://image.pollinations.ai/prompt/Fine%20botanical%20illustration%20of%20Leptinella%20squalida%2C%20traditional%20ukiyo-e%20woodblock%20print%20style%2C%20natural%20botanical%20colors%2C%20precise%20ink%20outlines%2C%20ivory%20paper%20texture%2C%20full%20plant%20with%20stem%20leaves%20and%20flowers%2C%20botanically%20accurate%2C%20soft%20watercolor%20wash%2C%20no%20text%2C%20no%20labels%2C%20museum%20quality%20print?width=800&height=920&seed=42067&nologo=true&t=1783842918"
  },
  {
    "date": "2026-07-12 07:51",
    "city": "Lima",
    "country": "Peru",
    "latin": "Passiflora caerulea",
    "common": "Blue Passion Flower",
    "note": "Unfurling tenderly in winter's warmth",
    "phenology": "Flowering",
    "compound_name": "Passiflorin",
    "compound": "Rare flavonoid with sedative properties",
    "season": "Winter",
    "temp": 20,
    "condition": "Partly cloudy",
    "image_url": "https://image.pollinations.ai/prompt/Fine%20botanical%20illustration%20of%20Passiflora%20caerulea%2C%20traditional%20ukiyo-e%20woodblock%20print%20style%2C%20natural%20botanical%20colors%2C%20precise%20ink%20outlines%2C%20ivory%20paper%20texture%2C%20full%20plant%20with%20stem%20leaves%20and%20flowers%2C%20botanically%20accurate%2C%20soft%20watercolor%20wash%2C%20no%20text%2C%20no%20labels%2C%20museum%20quality%20print?width=800&height=920&seed=21499&nologo=true"
  },
  {
    "date": "2026-07-12 03:20",
    "city": "Tbilisi",
    "country": "Georgia",
    "latin": "Galium verum",
    "common": "Lady's Bedstraw",
    "note": "Blooming under humid skies",
    "phenology": "Flowering",
    "compound_name": "Asperuloside",
    "compound": "Rare due to complex synthesis",
    "season": "Summer",
    "temp": 21,
    "condition": "Showers",
    "image_url": "https://image.pollinations.ai/prompt/Fine%20botanical%20illustration%20of%20Galium%20verum%2C%20traditional%20ukiyo-e%20woodblock%20print%20style%2C%20natural%20botanical%20colors%2C%20precise%20ink%20outlines%2C%20ivory%20paper%20texture%2C%20full%20plant%20with%20stem%20leaves%20and%20flowers%2C%20botanically%20accurate%2C%20soft%20watercolor%20wash%2C%20no%20text%2C%20no%20labels%2C%20museum%20quality%20print?width=800&height=920&seed=33396&nologo=true"
  },
  {
    "date": "2026-07-12 03:05",
    "city": "Cape Town",
    "country": "South Africa",
    "latin": "Pelargonium cucullatum",
    "common": "Wildemalva",
    "note": "Unfurling delicate pink petals slowly",
    "phenology": "Budding",
    "compound_name": "Geraniol",
    "compound": "Rare antioxidant properties found",
    "season": "Winter",
    "temp": 10,
    "condition": "Partly cloudy",
    "image_url": "https://image.pollinations.ai/prompt/Fine%20botanical%20illustration%20of%20Pelargonium%20cucullatum%2C%20traditional%20ukiyo-e%20woodblock%20print%20style%2C%20natural%20botanical%20colors%2C%20precise%20ink%20outlines%2C%20ivory%20paper%20texture%2C%20full%20plant%20with%20stem%20leaves%20and%20flowers%2C%20botanically%20accurate%2C%20soft%20watercolor%20wash%2C%20no%20text%2C%20no%20labels%2C%20museum%20quality%20print?width=800&height=920&seed=2866&nologo=true"
  },
  {
    "date": "2026-07-12 02:53",
    "city": "Sydney",
    "country": "Australia",
    "latin": "Leptinella squallida",
    "common": "Bronze Carpet",
    "note": "Bronze foliage glistens",
    "phenology": "Dormant",
    "compound_name": "Flavonoids",
    "compound": "Powerful antioxidants abound",
    "season": "Winter",
    "temp": 15,
    "condition": "Clear sky",
    "image_url": "https://image.pollinations.ai/prompt/Fine%20botanical%20illustration%20of%20Leptinella%20squallida%2C%20traditional%20ukiyo-e%20woodblock%20print%20style%2C%20natural%20botanical%20colors%2C%20precise%20ink%20outlines%2C%20ivory%20paper%20texture%2C%20full%20plant%20with%20stem%20leaves%20and%20flowers%2C%20botanically%20accurate%2C%20soft%20watercolor%20wash%2C%20no%20text%2C%20no%20labels%2C%20museum%20quality%20print?width=800&height=920&seed=95087&nologo=true"
  }
]